pytnt/TNTdtypes.py
pytnt/__init__.py
pytnt/find_TNMR_backup_files.py
pytnt/processTNT.py
pytnt/utils.py
pytnt-0.1.0.dist-info/BSD-3-Clause.txt
pytnt-0.1.0.dist-info/CC0-1.0.txt
pytnt-0.1.0.dist-info/GPL-3.0-or-later.txt
pytnt-0.1.0.dist-info/METADATA
pytnt-0.1.0.dist-info/WHEEL
pytnt-0.1.0.dist-info/entry_points.txt
pytnt-0.1.0.dist-info/top_level.txt
pytnt-0.1.0.dist-info/RECORD
