Metadata-Version: 2.1
Name: pytnt
Version: 0.1.0
Summary: Read NMR data files in the TecMag .tnt file format
Home-page: https://github.com/chatcannon/pytnt
Author: Chris Kerr
Author-email: chris.kerr@mykolab.ch
License: GPLv3+
Platform: UNKNOWN
Classifier: Development Status :: 3 - Alpha
Classifier: Programming Language :: Python :: 2.7
Classifier: Programming Language :: Python :: 3
Classifier: Intended Audience :: Developers
Classifier: Intended Audience :: Science/Research
Classifier: License :: OSI Approved :: GNU General Public License v3 or later (GPLv3+)
Classifier: Natural Language :: English
Classifier: Topic :: Scientific/Engineering :: Chemistry
Requires-Python: >=2.7
Requires-Dist: numpy
